otto_mcp/__init__.py
otto_mcp/server.py
otto_mcp-1.0.1.dist-info/licenses/LICENSE
otto_mcp-1.0.1.dist-info/METADATA
otto_mcp-1.0.1.dist-info/WHEEL
otto_mcp-1.0.1.dist-info/entry_points.txt
otto_mcp-1.0.1.dist-info/top_level.txt
otto_mcp-1.0.1.dist-info/RECORD
