Metadata-Version: 2.4
Name: otto-mcp
Version: 1.0.1
Summary: MCP server for Otto cognitive safety layer - ThinkingMachines [He2025] compliant
Author: Otto Contributors
License: MIT
Project-URL: Homepage, https://github.com/JosephOIbrahim/otto-os
Project-URL: Documentation, https://github.com/JosephOIbrahim/otto-os#readme
Project-URL: Repository, https://github.com/JosephOIbrahim/otto-os
Project-URL: Issues, https://github.com/JosephOIbrahim/otto-os/issues
Keywords: mcp,model-context-protocol,otto,cognitive,safety,claude,anthropic,llm,thinkingmachines
Classifier: Development Status :: 4 - Beta
Classifier: Intended Audience :: Developers
Classifier: License :: OSI Approved :: MIT License
Classifier: Operating System :: OS Independent
Classifier: Programming Language :: Python :: 3
Classifier: Programming Language :: Python :: 3.10
Classifier: Programming Language :: Python :: 3.11
Classifier: Programming Language :: Python :: 3.12
Classifier: Programming Language :: Python :: 3.13
Classifier: Topic :: Software Development :: Libraries :: Python Modules
Classifier: Topic :: Scientific/Engineering :: Artificial Intelligence
Requires-Python: >=3.10
License-File: LICENSE
Requires-Dist: otto-os>=0.6.0
Requires-Dist: mcp>=1.0.0
Provides-Extra: dev
Requires-Dist: pytest>=7.0.0; extra == "dev"
Dynamic: license-file
